yarrtist/__init__.py
yarrtist/_version.py
yarrtist/_version.pyi
yarrtist/py.typed
yarrtist/cli/__init__.py
yarrtist/cli/__main__.py
yarrtist/cli/globals.py
yarrtist/cli/main.py
yarrtist/cli/plot_config.py
yarrtist/cli/plot_connectivity.py
yarrtist/cli/plot_scan.py
yarrtist/cli/plot_test.py
yarrtist/plotter/__init__.py
yarrtist/plotter/core_functions.py
yarrtist/utils/__init__.py
yarrtist/utils/utils.py
yarrtist/utils/fonts/Roboto_Condensed-BoldItalic.ttf
yarrtist/utils/fonts/__init__.py
yarrtist-1.1.2.dist-info/METADATA
yarrtist-1.1.2.dist-info/WHEEL
yarrtist-1.1.2.dist-info/entry_points.txt
yarrtist-1.1.2.dist-info/licenses/LICENSE
yarrtist-1.1.2.dist-info/RECORD
